PythonOneToMillion/README.md
PythonOneToMillion/__init__.py
PythonOneToMillion/__main__.py
PythonOneToMillion/file.epub
PythonOneToMillion/index.html
PythonOneToMillion/css/__init__.py
PythonOneToMillion/css/annotations.css
PythonOneToMillion/css/main.css
PythonOneToMillion/css/normalize.css
PythonOneToMillion/css/popup.css
PythonOneToMillion/font/__init__.py
PythonOneToMillion/font/fontello.eot
PythonOneToMillion/font/fontello.svg
PythonOneToMillion/font/fontello.ttf
PythonOneToMillion/font/fontello.woff
PythonOneToMillion/img/__init__.py
PythonOneToMillion/img/annotator-glyph-sprite.png
PythonOneToMillion/img/annotator-icon-sprite.png
PythonOneToMillion/img/apple-touch-icon.png
PythonOneToMillion/img/cancelfullscreen.png
PythonOneToMillion/img/close.png
PythonOneToMillion/img/fullscreen.png
PythonOneToMillion/img/loader.gif
PythonOneToMillion/img/menu-icon.png
PythonOneToMillion/img/save.png
PythonOneToMillion/img/saved.png
PythonOneToMillion/img/settings-s.png
PythonOneToMillion/img/settings.png
PythonOneToMillion/img/star.png
PythonOneToMillion/js/__init__.py
PythonOneToMillion/js/epub.js
PythonOneToMillion/js/epub.min.js
PythonOneToMillion/js/epub.min.map
PythonOneToMillion/js/hooks.min.js
PythonOneToMillion/js/hooks.min.map
PythonOneToMillion/js/reader.js
PythonOneToMillion/js/reader.js.map
PythonOneToMillion/js/reader.min.js
PythonOneToMillion/js/reader.min.map
PythonOneToMillion/js/hooks/__init__.py
PythonOneToMillion/js/hooks/extensions/__init__.py
PythonOneToMillion/js/hooks/extensions/highlight.js
PythonOneToMillion/js/libs/__init__.py
PythonOneToMillion/js/libs/jquery.min.js
PythonOneToMillion/js/libs/localforage.min.js
PythonOneToMillion/js/libs/screenfull.js
PythonOneToMillion/js/libs/screenfull.min.js
PythonOneToMillion/js/libs/zip.min.js
PythonOneToMillion/js/plugins/__init__.py
PythonOneToMillion/js/plugins/hypothesis.js
PythonOneToMillion/js/plugins/search.js
python_one_to_million-2024.3.4.0.dist-info/METADATA
python_one_to_million-2024.3.4.0.dist-info/WHEEL
python_one_to_million-2024.3.4.0.dist-info/entry_points.txt
python_one_to_million-2024.3.4.0.dist-info/top_level.txt
python_one_to_million-2024.3.4.0.dist-info/RECORD
